<annotation>
	<folder></folder>
	<filename>maiale121_jpg.rf.85e10056f0b794dececaf9327455d199.jpg</filename>
	<path>maiale121_jpg.rf.85e10056f0b794dececaf9327455d199.jpg</path>
	<source>
		<database>roboflow.ai</database>
	</source>
	<size>
		<width>320</width>
		<height>320</height>
		<depth>3</depth>
	</size>
	<segmented>0</segmented>
	<object>
		<name>pig</name>
		<pose>Unspecified</pose>
		<truncated>0</truncated>
		<difficult>0</difficult>
		<occluded>0</occluded>
		<bndbox>
			<xmin>133</xmin>
			<xmax>201</xmax>
			<ymin>45</ymin>
			<ymax>89</ymax>
		</bndbox>
	</object>
</annotation>
